container_transform/__init__.py
container_transform/chronos.py
container_transform/client.py
container_transform/compose.py
container_transform/converter.py
container_transform/ecs.py
container_transform/marathon.py
container_transform/schema.py
container_transform/systemd.py
container_transform/transformer.py
container_transform/version.py
container_transform/tests/__init__.py
container_transform/tests/base_transformer_tests.py
container_transform/tests/chronos_tests.py
container_transform/tests/client_tests.py
container_transform/tests/compose_tests.py
container_transform/tests/converter_tests.py
container_transform/tests/ecs_tests.py
container_transform/tests/marathon_tests.py
container_transform/tests/systemd_tests.py
container_transform-1.1.4.dist-info/DESCRIPTION.rst
container_transform-1.1.4.dist-info/METADATA
container_transform-1.1.4.dist-info/RECORD
container_transform-1.1.4.dist-info/WHEEL
container_transform-1.1.4.dist-info/entry_points.txt
container_transform-1.1.4.dist-info/metadata.json
container_transform-1.1.4.dist-info/top_level.txt
