Metadata-Version: 2.0
Name: container-transform
Version: 1.1.4
Summary: A converter for various docker cluster formats
Home-page: https://github.com/micahhausler/container-transform
Author: Micah  Hausler
Author-email: hausler.m@gmail.com
License: MIT
Keywords: docker,container,fig,ecs,compose
Platform: UNKNOWN
Classifier: Programming Language :: Python :: 3.5
Classifier: Intended Audience :: Developers
Classifier: License :: OSI Approved :: MIT License
Classifier: Operating System :: OS Independent
Requires-Dist: Jinja2 (>=2.7.0)
Requires-Dist: PyYAML (>=3.10,<4)
Requires-Dist: click (>=3.3)
Provides-Extra: all
Requires-Dist: Jinja2 (>=2.7.0); extra == 'all'
Requires-Dist: PyYAML (>=3.10,<4); extra == 'all'
Requires-Dist: Sphinx (>=1.2.2); extra == 'all'
Requires-Dist: click (>=3.3); extra == 'all'
Requires-Dist: coverage (>=4.0.3); extra == 'all'
Requires-Dist: flake8 (>=2.2.0); extra == 'all'
Requires-Dist: mock (>=1.0.1); extra == 'all'
Requires-Dist: nose (>=1.3.0); extra == 'all'
Requires-Dist: sphinx-rtd-theme; extra == 'all'
Requires-Dist: wheel; extra == 'all'
Provides-Extra: docs
Requires-Dist: Sphinx (>=1.2.2); extra == 'docs'
Requires-Dist: sphinx-rtd-theme; extra == 'docs'
Provides-Extra: packaging
Requires-Dist: wheel; extra == 'packaging'
Provides-Extra: test
Requires-Dist: coverage (>=4.0.3); extra == 'test'
Requires-Dist: flake8 (>=2.2.0); extra == 'test'
Requires-Dist: mock (>=1.0.1); extra == 'test'
Requires-Dist: nose (>=1.3.0); extra == 'test'
